pvfr/groopledb/__init__.py
pvfr/groopledb/activity.py
pvfr/groopledb/category.py
pvfr/groopledb/config.yml
pvfr/groopledb/group.py
pvfr/groopledb/organizer.py
pvfr/groopledb/participant.py
pvfr.groopledb-0.5.0.dist-info/LICENSE
pvfr.groopledb-0.5.0.dist-info/METADATA
pvfr.groopledb-0.5.0.dist-info/WHEEL
pvfr.groopledb-0.5.0.dist-info/top_level.txt
pvfr.groopledb-0.5.0.dist-info/RECORD
