Metadata-Version: 2.1
Name: pvfr.groopledb
Version: 0.5.0
Summary: Package to read data from the Groople MySQL Database
Home-page: https://github.com/passeport-vacances/groopledb
Author: Jacques Supcik
Author-email: jacques@pvfr.ch
License: UNKNOWN
Platform: UNKNOWN
Classifier: Programming Language :: Python :: 3.6
Classifier: License :: OSI Approved :: Apache Software License
Classifier: Operating System :: OS Independent
Requires-Dist: PyMySQL
Requires-Dist: PyYAML
Requires-Dist: records
Requires-Dist: email-validator
